pyint/__init__.py
pyint/decoder.py
pyint/encoder.py
pyint-1.0.0.dist-info/DESCRIPTION.rst
pyint-1.0.0.dist-info/METADATA
pyint-1.0.0.dist-info/RECORD
pyint-1.0.0.dist-info/WHEEL
pyint-1.0.0.dist-info/metadata.json
pyint-1.0.0.dist-info/top_level.txt
