Metadata-Version: 2.0
Name: pyint
Version: 1.0.0
Summary: Python implementation of protobuf style varints
Home-page: https://github.com/Projjol/pyint
Author: Projjol Banerji
Author-email: ping@projjol.me
License: UNKNOWN
Platform: UNKNOWN
Classifier: Programming Language :: Python :: 3
Classifier: License :: OSI Approved :: MIT License
